ciak/ciak.py
ciak/ciak36.py
ciak/ciak36.pyz
ciak/generate_ciak36.sh
ciak/test.org
ciak-0.1.0.dist-info/entry_points.txt
ciak-0.1.0.dist-info/LICENSE
ciak-0.1.0.dist-info/WHEEL
ciak-0.1.0.dist-info/METADATA
ciak-0.1.0.dist-info/RECORD
