Metadata-Version: 2.1
Name: ciak
Version: 0.1.0
Summary: Run executables according to a configuration file
Home-page: https://github.com/sbozzolo/ciak
License: GPL-3.0-or-later
Author: Gabriele Bozzola
Author-email: sbozzolator@gmail.com
Requires-Python: >=3.6.2,<4.0.0
Classifier: License :: OSI Approved :: GNU General Public License v3 or later (GPLv3+)
Classifier: Programming Language :: Python :: 3
Classifier: Programming Language :: Python :: 3.7
Classifier: Programming Language :: Python :: 3.8
Classifier: Programming Language :: Python :: 3.9
Classifier: Programming Language :: Python :: 3.10
Classifier: Programming Language :: Python :: 3.11
Project-URL: Bug Tracker, https://github.com/sbozzolo/ciak/issues
Project-URL: Repository, https://github.com/sbozzolo/ciak
